viberun/__init__.py
viberun/__main__.py
viberun/cli.py
viberun/vendor/aarch64-apple-darwin/viberun/viberun
viberun/vendor/aarch64-pc-windows-msvc/viberun/viberun.exe
viberun/vendor/aarch64-unknown-linux-musl/viberun/viberun
viberun/vendor/x86_64-apple-darwin/viberun/viberun
viberun/vendor/x86_64-pc-windows-msvc/viberun/viberun.exe
viberun/vendor/x86_64-unknown-linux-musl/viberun/viberun
viberun-0.5.4.dist-info/licenses/LICENSE
viberun-0.5.4.dist-info/METADATA
viberun-0.5.4.dist-info/WHEEL
viberun-0.5.4.dist-info/entry_points.txt
viberun-0.5.4.dist-info/top_level.txt
viberun-0.5.4.dist-info/RECORD
